geofetchr/__init__.py
geofetchr/download.py
geofetchr/group.py
geofetchr/metadata.py
geofetchr/search.py
geofetchr-0.1.4.dist-info/METADATA
geofetchr-0.1.4.dist-info/WHEEL
geofetchr-0.1.4.dist-info/licenses/LICENSE.txt
geofetchr-0.1.4.dist-info/RECORD
