Metadata-Version: 2.4
Name: geofetchr
Version: 0.1.4
Summary: A Python package to search and organize GEO datasets by keyword, organism, assay type, find metadata and download.
Project-URL: Documentation, https://github.com/Maaruuuf/geofetchr#readme
Project-URL: Issues, https://github.com/Maaruuuf/geofetchr/issues
Project-URL: Source, https://github.com/Maaruuuf/geofetchr
Author-email: Maaruuuf <abc.maruf12@gmail.com>
License-Expression: MIT
License-File: LICENSE.txt
Classifier: Development Status :: 4 - Beta
Classifier: Programming Language :: Python
Classifier: Programming Language :: Python :: 3.10
Classifier: Programming Language :: Python :: 3.11
Classifier: Programming Language :: Python :: 3.12
Requires-Python: >=3.10
Requires-Dist: geoparse>=2.0.4
Requires-Dist: pandas>=2.3.1
Requires-Dist: requests>=2.32.5
